deeplotyper/__init__.py
deeplotyper/alignment_utils.py
deeplotyper/coordinate_utils.py
deeplotyper/data_models.py
deeplotyper/mapper.py
deeplotyper/orf_utils.py
deeplotyper/remapper.py
deeplotyper/vcf_haploevents.py
deeplotyper-2025.10.2a0.dist-info/licenses/LICENSE
deeplotyper-2025.10.2a0.dist-info/METADATA
deeplotyper-2025.10.2a0.dist-info/WHEEL
deeplotyper-2025.10.2a0.dist-info/top_level.txt
deeplotyper-2025.10.2a0.dist-info/RECORD
