Metadata-Version: 2.4
Name: deeplotyper
Version: 2025.10.2a0
Summary: Tools for graph based and string based mapping and remapping genomic ↔ transcript ↔ aminoacid sequences.
Author-email: Eli Niktab <maniktab@gmail.com>
License:                                  Apache License
Project-URL: Source, https://github.com/eniktab/deeplotyper
Project-URL: Tracker, https://github.com/eniktab/deeplotyper/issues
Keywords: vcf,coordinate,haplotype,graph,protein,isoform
Classifier: Development Status :: 4 - Beta
Classifier: License :: OSI Approved :: MIT License
Classifier: Programming Language :: Python
Classifier: Programming Language :: Python :: 3.8
Classifier: Programming Language :: Python :: 3.9
Classifier: Programming Language :: Python :: 3.10
Classifier: Programming Language :: Python :: 3.11
Classifier: Programming Language :: Python :: 3.12
Classifier: Topic :: Scientific/Engineering :: Bio-Informatics
Requires-Python: >=3.8
License-File: LICENSE
Requires-Dist: biopython>=1.78
Requires-Dist: pysam>=0.19
Provides-Extra: testing
Requires-Dist: pytest>=6.0; extra == "testing"
Provides-Extra: docs
Requires-Dist: sphinx>=4.0; extra == "docs"
Requires-Dist: sphinx-autodoc-typehints; extra == "docs"
Requires-Dist: sphinx_rtd_theme; extra == "docs"
Provides-Extra: lint
Requires-Dist: flake8<5.0,>=3.8; extra == "lint"
Requires-Dist: mypy<1.0,>=0.900; extra == "lint"
Provides-Extra: dev
Requires-Dist: biopython; extra == "dev"
Requires-Dist: pysam; extra == "dev"
Requires-Dist: bumpver; extra == "dev"
Requires-Dist: pytest; extra == "dev"
Dynamic: license-file
